neon_messagebus_mq_connector/__init__.py
neon_messagebus_mq_connector/__main__.py
neon_messagebus_mq_connector/config.py
neon_messagebus_mq_connector/controller.py
neon_messagebus_mq_connector/enums.py
neon_messagebus_mq_connector/messages.py
neon_messagebus_mq_connector-1.0.0.dist-info/LICENSE.md
neon_messagebus_mq_connector-1.0.0.dist-info/METADATA
neon_messagebus_mq_connector-1.0.0.dist-info/WHEEL
neon_messagebus_mq_connector-1.0.0.dist-info/top_level.txt
neon_messagebus_mq_connector-1.0.0.dist-info/RECORD
