Metadata-Version: 2.1
Name: neon-messagebus-mq-connector
Version: 1.0.0
Summary: MQ-Messagebus Connector Module
Home-page: https://github.com/neongeckocom/neon-messagebus-mq-connector
Author: Neongecko
Author-email: developers@neon.ai
License: BSD-3-Clause
Classifier: Programming Language :: Python :: 3
Classifier: Operating System :: OS Independent
Requires-Python: >=3.6
License-File: LICENSE.md
Requires-Dist: neon-utils[network]~=1.0
Requires-Dist: pydantic<3.0,>=1.9
Requires-Dist: neon-mq-connector~=0.6
Requires-Dist: ovos-config>=0.0.3,~=0.0
Requires-Dist: ovos-bus-client>=0.0.4,~=0.0
